lxutils/__init__.py
lxutils/correct_asyncio.py
lxutils/log.py
lxutils/read_config.py
lxutils/read_latest_csv.py
lxutils/test_utils.py
lxutils-0.0.2.dist-info/LICENSE
lxutils-0.0.2.dist-info/METADATA
lxutils-0.0.2.dist-info/WHEEL
lxutils-0.0.2.dist-info/top_level.txt
lxutils-0.0.2.dist-info/RECORD
