Metadata-Version: 2.1
Name: lxutils
Version: 0.0.2
Summary: Various utilities written by Alexey Leshchenko
Home-page: https://github.com/leshchenko1979/lxutils
Author: Alexey Leshchenko
Author-email: leshchenko@gmail.com
License: MIT
Platform: UNKNOWN
Classifier: Programming Language :: Python :: 3
Classifier: License :: OSI Approved :: MIT License
Classifier: Operating System :: OS Independent
Requires-Python: >=3.6
